eml_parser/__init__.py
eml_parser/email_cleaner.py
eml_parser/email_parser.py
eml_parser/exceptions.py
eml_parser/helper.py
eml_parser/icon_email.py
eml_parser/icon_file.py
eml_parser/indicators.py
eml_parser/microsoft_newline_cleaner.py
unit_test/__init__.py
unit_test/payload_cleaner.py
unit_test/test_email_cleaner.py
unit_test/test_email_parser.py
unit_test/test_icon_email.py
unit_test/test_icon_file.py
python_eml_parser-2.0.1.dist-info/LICENSE
python_eml_parser-2.0.1.dist-info/METADATA
python_eml_parser-2.0.1.dist-info/WHEEL
python_eml_parser-2.0.1.dist-info/entry_points.txt
python_eml_parser-2.0.1.dist-info/top_level.txt
python_eml_parser-2.0.1.dist-info/RECORD
