Metadata-Version: 2.1
Name: python-eml-parser
Version: 2.0.1
Summary: Rapid7 InsightConnect email parser for email plugins
Home-page: https://github.com/rapid7/python-eml-parser
Author: Rapid7 Integrations Alliance
Author-email: integrationalliance@rapid7.com
License: MIT
Classifier: Programming Language :: Python :: 3
Classifier: Operating System :: OS Independent
Classifier: Intended Audience :: Developers
Classifier: License :: OSI Approved :: MIT License
Classifier: Natural Language :: English
License-File: LICENSE
